LICENSE
README.md
setup.py
ctime/__init__.py
ctime.egg-info/PKG-INFO
ctime.egg-info/SOURCES.txt
ctime.egg-info/dependency_links.txt
ctime.egg-info/top_level.txt